micropython_bma400/__init__.py
micropython_bma400/bma400.py
micropython_bma400/i2c_helpers.py
micropython_bma400-0.1.2.dist-info/LICENSE
micropython_bma400-0.1.2.dist-info/METADATA
micropython_bma400-0.1.2.dist-info/WHEEL
micropython_bma400-0.1.2.dist-info/top_level.txt
micropython_bma400-0.1.2.dist-info/RECORD
