Metadata-Version: 2.1
Name: micropython-bma400
Version: 0.1.2
Summary: MicroPython Driver for the Bosch BMA400 Accelerometer
Author-email: JDM <xxyx@mailmeto.mozmail.com>
License: MIT
Project-URL: Homepage, https://github.com/jposada202020/MicroPython_BMA400
Keywords: sensor,micropython,bma400,acceleration,gravity,sensor,bosch,accelerometer
Classifier: Intended Audience :: Developers
Classifier: Topic :: Software Development :: Libraries
Classifier: Topic :: Software Development :: Embedded Systems
Classifier: Topic :: System :: Hardware
Classifier: License :: OSI Approved :: MIT License
Classifier: Programming Language :: Python :: Implementation :: MicroPython
License-File: LICENSE
